{"_id":"ionic-gulp-fonts-copy","_rev":"1-78c8c630126d5b7bffa60b548eff3d4e","name":"ionic-gulp-fonts-copy","description":"Gulp task for Ionic projects to copy Ionic fonts to a build directory","dist-tags":{"latest":"1.0.0"},"versions":{"1.0.0":{"name":"ionic-gulp-fonts-copy","description":"Gulp task for Ionic projects to copy Ionic fonts to a build directory","version":"1.0.0","dependencies":{"gulp":"^3.9.1"},"_id":"ionic-gulp-fonts-copy@1.0.0","scripts":{},"_shasum":"9d9fd6600a3b2c5132aa4701aa41186b9fba8054","_from":".","_npmVersion":"3.8.1","_nodeVersion":"0.12.4","_npmUser":{"name":"tlancina","email":"tim@ionic.io"},"dist":{"shasum":"9d9fd6600a3b2c5132aa4701aa41186b9fba8054","tarball":"https://registry.npmjs.org/ionic-gulp-fonts-copy/-/ionic-gulp-fonts-copy-1.0.0.tgz"},"maintainers":[{"name":"tlancina","email":"tim@ionic.io"}],"_npmOperationalInternal":{"host":"packages-12-west.internal.npmjs.com","tmp":"tmp/ionic-gulp-fonts-copy-1.0.0.tgz_1458060090129_0.8752205308992416"},"directories":{}}},"readme":"# Fonts Copy Task\nCopy Ionic fonts to build directory.\n\n## API\n\n### copyFonts([options])\n\nReturns a [stream](http://nodejs.org/api/stream.html) of [Vinyl files](https://github.com/wearefractal/vinyl-fs)\nthat can be [piped](http://nodejs.org/api/stream.html#stream_readable_pipe_destination_options).\n\n#### Available options:\n- **src** (String|Array) Glob or array of globs ([What's a glob?](https://github.com/isaacs/node-glob#glob-primer)) matching font source files. Default: `'node_modules/ionic-angular/fonts/**/*.+(ttf|woff|woff2)'`.\n- **dest** (String) Output path for the fonts. Default: `'www/build/fonts'`.\n\n## Example\n\n```\nvar copyFonts = require('ionic-gulp-fonts-copy');\n\ngulp.task('fonts', copyFonts);\n\ngulp.task('fonts', function(){\n  return copyFonts({ dest: 'www/my-custom-build-dir'});\n});\n```\n\n\n\n\n\n\n","maintainers":[{"name":"tlancina","email":"tim@ionic.io"}],"time":{"modified":"2016-03-15T16:41:32.569Z","created":"2016-03-15T16:41:32.569Z","1.0.0":"2016-03-15T16:41:32.569Z"},"readmeFilename":"README.md","_attachments":{},"_etag":"\"ALWHYJ0A3JQCI7YRJL202VDXG\""}